rumes/__init__.py
rumes/core.py
rumes-0.0.1.dist-info/METADATA
rumes-0.0.1.dist-info/WHEEL
rumes-0.0.1.dist-info/top_level.txt
rumes-0.0.1.dist-info/RECORD
