Metadata-Version: 2.4
Name: rumes
Version: 0.0.1
Summary: A small sample python
Author-email: Abhishek <abhithakur488198@gmail.com>
Project-URL: Homepage, https://github.com/pypa/sampleproject
Project-URL: Issues, https://github.com/pypa/sampleproject/issues
Classifier: Programming Language :: Python :: 3
Classifier: Operating System :: OS Independent
Requires-Python: >=3.9
